HE_Data/__init__.py
HE_Data/adm1.csv
HE_Data/cmp1.csv
HE_Data/crs1.csv
HE_Data/data.py
HE_Data/enr1.csv
csulb_mock_dataset/__init__.py
csulb_mock_dataset/cmp1.csv
csulb_mock_dataset/data.py
csulb_mock_student_dataset/__init__.py
csulb_mock_student_dataset/cmp1.csv
csulb_mock_student_dataset/data.py
files/__init__.py
files/data.py
HE_Data-0.0.2.dist-info/METADATA
HE_Data-0.0.2.dist-info/WHEEL
HE_Data-0.0.2.dist-info/top_level.txt
HE_Data-0.0.2.dist-info/RECORD
