Metadata-Version: 2.1
Name: HE-Data
Version: 0.0.2
Summary: A simple package containing a CSV dataset
Author: Gurucharan Raju
Author-email: Gurucharan.Raju-SA@csulb.edu
License: MIT
Requires-Dist: pandas
